agent.py
setup.cfg
setup.py
agent.egg-info/PKG-INFO
agent.egg-info/SOURCES.txt
agent.egg-info/dependency_links.txt
agent.egg-info/pbr.json
agent.egg-info/top_level.txt