Metadata-Version: 1.1
Name: agent
Version: 0.1.0
Summary: Async generators for humans
Home-page: https://github.com/chrisseto/Agent
Author: Chris Seto
Author-email: chriskseto@gmail.com
License: The MIT License (MIT)
